AEngine/.git/COMMIT_EDITMSG
AEngine/.git/config
AEngine/.git/description
AEngine/.git/FETCH_HEAD
AEngine/.git/HEAD
AEngine/.git/hooks/applypatch-msg.sample
AEngine/.git/hooks/commit-msg.sample
AEngine/.git/hooks/fsmonitor-watchman.sample
AEngine/.git/hooks/post-update.sample
AEngine/.git/hooks/pre-applypatch.sample
AEngine/.git/hooks/pre-commit.sample
AEngine/.git/hooks/pre-merge-commit.sample
AEngine/.git/hooks/pre-push.sample
AEngine/.git/hooks/pre-rebase.sample
AEngine/.git/hooks/pre-receive.sample
AEngine/.git/hooks/prepare-commit-msg.sample
AEngine/.git/hooks/push-to-checkout.sample
AEngine/.git/hooks/update.sample
AEngine/.git/index
AEngine/.git/info/exclude
AEngine/.git/logs/HEAD
AEngine/.git/logs/refs/heads/main
AEngine/.git/logs/refs/remotes/origin/HEAD
AEngine/.git/logs/refs/remotes/origin/main
AEngine/.git/objects/0d/0d75ec0f442a8757deb457ea034d8c7c3de29d
AEngine/.git/objects/24/c7aedb7034cbf2a3d60aa57173391d142497fa
AEngine/.git/objects/34/cef1fab4e3cffef109ec055fa1c47e7e5c3be0
AEngine/.git/objects/46/4a21589dfd6631ad50e5f897bcb966b429e68d
AEngine/.git/objects/66/23a3da4bdcdc18dbd5ab1d7c3225a47513768d
AEngine/.git/objects/6c/583912c0082cd0f2f78422422a2037bf1911d1
AEngine/.git/objects/6e/7ce151650b2fe1f791898f6a95a43b1c9865f8
AEngine/.git/objects/6f/7f3ecc30916234624ee9a312113cd0b7f2cc14
AEngine/.git/objects/79/8d6fc9fde6db3ed9d39566ec85a6b03c5a9546
AEngine/.git/objects/80/fc3202b9b75d9531e83029737d1a04e24c860c
AEngine/.git/objects/8c/1539a690052cb4d307290f1f10a3d4c17a33f3
AEngine/.git/objects/8d/52d62878eeecf2655eb3e7b741c775756af711
AEngine/.git/objects/b3/46bae22e5ed9b2760a5007e8f829bf994cca15
AEngine/.git/objects/cc/13e4f190803eef685107ba908141bb08cf682c
AEngine/.git/objects/d1/68d4b6eecb9c988f99c58f9ded60dfbbf84a3a
AEngine/.git/objects/d8/7c856b798f9366e3de8d7ac7238d9e7e633f23
AEngine/.git/objects/d9/e44940da23009dca4a660d3c7ff71791fd8c9c
AEngine/.git/objects/e4/29b027aa10b98804f7ceee61dabe9831c6ffed
aengine-1.0.52.dist-info/WHEEL
aengine-1.0.52.dist-info/METADATA
aengine-1.0.52.dist-info/RECORD
